django_simplekeys-0.5.3.dist-info/METADATA
django_simplekeys-0.5.3.dist-info/RECORD
django_simplekeys-0.5.3.dist-info/WHEEL
django_simplekeys-0.5.3.dist-info/top_level.txt
example/__init__.py
example/settings.py
example/wsgi.py
simplekeys/__init__.py
simplekeys/admin.py
simplekeys/apps.py
simplekeys/backends.py
simplekeys/decorators.py
simplekeys/forms.py
simplekeys/middleware.py
simplekeys/models.py
simplekeys/verifier.py
simplekeys/views.py
simplekeys/management/__init__.py
simplekeys/management/commands/__init__.py
simplekeys/management/commands/exportkeys.py
simplekeys/management/commands/usagereport.py
simplekeys/migrations/0001_initial.py
simplekeys/migrations/0002_auto_20170421_0307.py
simplekeys/migrations/0003_auto_20181030_0030.py
simplekeys/migrations/__init__.py
simplekeys/templates/simplekeys/confirmation.html
simplekeys/templates/simplekeys/confirmation_email.txt
simplekeys/templates/simplekeys/confirmed.html
simplekeys/templates/simplekeys/register.html
simplekeys/tests/__init__.py
simplekeys/tests/test_backends.py
simplekeys/tests/test_exportkeys.py
simplekeys/tests/test_middleware_and_decorator.py
simplekeys/tests/test_usagereport.py
simplekeys/tests/test_verifier.py
simplekeys/tests/test_views.py
simplekeys/tests/urls.py
simplekeys/tests/views.py
