Metadata-Version: 2.1
Name: django-simplekeys
Version: 0.5.3
Summary: Django API Key management & validation
Home-page: http://github.com/jamesturk/django-simplekeys/
Author: James Turk
Author-email: dev@jamesturk.net
License: MIT License
Platform: any
Classifier: Development Status :: 4 - Beta
Classifier: Intended Audience :: Developers
Classifier: License :: OSI Approved :: MIT License
Classifier: Natural Language :: English
Classifier: Operating System :: OS Independent
Classifier: Programming Language :: Python
Classifier: Environment :: Web Environment
Classifier: Programming Language :: Python :: 2
Classifier: Programming Language :: Python :: 2.7
Classifier: Programming Language :: Python :: 3
Classifier: Programming Language :: Python :: 3.5
Classifier: Programming Language :: Python :: 3.6
Classifier: Programming Language :: Python :: 3.7
Provides-Extra: dev
Requires-Dist: Django
Provides-Extra: dev
Requires-Dist: freezegun; extra == 'dev'
Requires-Dist: flake8; extra == 'dev'
Requires-Dist: sphinx; extra == 'dev'
Requires-Dist: sphinx-rtd-theme; extra == 'dev'
